LICENSE
MANIFEST.in
README.rst
setup.py
qroutes/__init__.py
qroutes/response.py
qroutes/router.py
qroutes.egg-info/PKG-INFO
qroutes.egg-info/SOURCES.txt
qroutes.egg-info/dependency_links.txt
qroutes.egg-info/top_level.txt